kemstem/__init__.py
kemstem/version.py
kemstem/atomic/__init__.py
kemstem/atomic/columnfind.py
kemstem/atomic/neighborhood.py
kemstem/atomic/periodicdistortion.py
kemstem/fourier/__init__.py
kemstem/fourier/fourierfilter.py
kemstem/fourier/peakpick.py
kemstem/fourier/phaselock.py
kemstem/fourier/strain.py
kemstem/fourier/wavefit.py
kemstem/util/__init__.py
kemstem/util/func.py
kemstem/util/general.py
kemstem/util/image.py
kemstem/util/point.py
kemstem/util/viz.py
kemstem-0.0.5.dist-info/licenses/LICENSE
kemstem-0.0.5.dist-info/METADATA
kemstem-0.0.5.dist-info/WHEEL
kemstem-0.0.5.dist-info/top_level.txt
kemstem-0.0.5.dist-info/RECORD
