Metadata-Version: 2.4
Name: kemstem
Version: 0.0.5
Summary: An atomic resolution STEM image analysis package developed in the Kourkoutis Electron Microscopy group at Cornell University.
Author-email: Noah Schnitzer <noah.i.schnitzer@gmail.com>
Project-URL: Homepage, https://github.com/noahschnitzer/kemstem
Project-URL: Issues, https://github.com/noahschnitzer/kemstem/issues
Keywords: Electron Microscopy,STEM
Classifier: Programming Language :: Python :: 3
Classifier: License :: OSI Approved :: GNU General Public License v3 (GPLv3)
Classifier: Operating System :: OS Independent
Requires-Python: >=3.8
License-File: LICENSE
Requires-Dist: scikit-learn
Requires-Dist: scikit-image
Requires-Dist: matplotlib
Requires-Dist: cmocean
Requires-Dist: scipy
Requires-Dist: tqdm
Requires-Dist: numpy
Dynamic: license-file
